{
  "batch_range in weeks": 6,
  "customers": {
    "96f55c7d8f42": {
      "created_at": "2017-01-06T12:46:46.384Z",
      "updated_at": null,
      "last_name": "Smith",
      "address": {
        "city": "Middletown",
        "state": "AK"
      },
      "events": [
        {
          "type": "visit",
          "key": "ac05e815502f",
          "effective_date": "2017-01-06T12:45:52.041Z",
          "week_id": "2017-01-01",
          "tags": [
            {
              "some key": "some value"
            }
          ]
        },
        {
          "type": "image upload",
          "key": "d8ede43b1d9f",
          "effective_date": "2017-01-06",
          "week_id": "2017-01-01",
          "action_data": {
            "camera_make": "Canon",
            "camera_model": "EOS 80D"
          }
        },
        {
          "type": "order",
          "key": "68d84e5d1a43",
          "effective_date": "2017-01-06T12:55:55.555Z",
          "updated_date": null,
          "week_id": "2017-01-01",
          "amount": 12.34
        },
        {
          "type": "visit",
          "key": "ac05e815502f",
          "effective_date": "2017-01-03T12:45:52.041Z",
          "week_id": "2017-01-01",
          "tags": [
            {
              "some key": "some value"
            }
          ]
        },
        {
          "type": "visit",
          "key": "ac05e815502a",
          "effective_date": "2017-01-20T12:45:52.041Z",
          "week_id": "2017-01-15",
          "tags": [
            {
              "some key": "some value"
            }
          ]
        },
        {
          "type": "image upload",
          "key": "d8ede43b1d9e",
          "effective_date": "2017-01-20",
          "week_id": "2017-01-15",
          "action_data": {
            "camera_make": "Canon",
            "camera_model": "EOS 80D"
          }
        },
        {
          "type": "order",
          "key": "68d84e5d1a41",
          "effective_date": "2017-01-20T12:55:55.555Z",
          "updated_date": null,
          "week_id": "2017-01-15",
          "amount": 40.34
        }
      ]
    },
    "96f55c7d8f41": {
      "created_at": "2017-01-06T12:46:46.384Z",
      "updated_at": null,
      "last_name": "John",
      "address": {
        "city": "Farmington",
        "state": "VA"
      },
      "events": [
        {
          "type": "visit",
          "key": "ac05e815502g",
          "effective_date": "2017-01-06T12:45:52.041Z",
          "week_id": "2017-01-01",
          "tags": [
            {
              "some key": "some value"
            }
          ]
        },
        {
          "type": "image upload",
          "key": "d8ede43b1d9g",
          "effective_date": "2017-01-06",
          "week_id": "2017-01-01",
          "action_data": {
            "camera_make": "Canon",
            "camera_model": "EOS 80D"
          }
        },
        {
          "type": "order",
          "key": "68d84e5d4a44",
          "effective_date": "2017-01-06T12:55:55.555Z",
          "updated_date": null,
          "week_id": "2017-01-01",
          "amount": 13.34
        },
        {
          "type": "visit",
          "key": "ac05e815502s",
          "effective_date": "2017-02-15T12:45:52.041Z",
          "week_id": "2017-02-12",
          "tags": [
            {
              "some key": "some value"
            }
          ]
        },
        {
          "type": "image upload",
          "key": "d8eden3b1d9b",
          "effective_date": "2017-02-15",
          "week_id": "2017-02-12",
          "action_data": {
            "camera_make": "Canon",
            "camera_model": "EOS 80D"
          }
        },
        {
          "type": "order",
          "key": "68d84e5j1a45",
          "effective_date": "2017-02-15T12:55:55.555Z",
          "updated_date": null,
          "week_id": "2017-02-12",
          "amount": 17.34
        },
        {
          "type": "visit",
          "key": "ac03e415502s",
          "effective_date": "2017-02-06T13:45:52.041Z",
          "week_id": "2017-02-05",
          "tags": [
            {
              "some key": "some value"
            }
          ]
        },
        {
          "type": "image upload",
          "key": "d8ehe47b1d9b",
          "effective_date": "2017-02-06",
          "week_id": "2017-02-05",
          "action_data": {
            "camera_make": "Canon",
            "camera_model": "EOS 80D"
          }
        },
        {
          "type": "order",
          "key": "68d84e81a45",
          "effective_date": "2017-02-06T13:55:55.555Z",
          "updated_date": null,
          "week_id": "2017-02-05",
          "amount": 5.48
        }
      ]
    }
  }
}